odoo8_addon_attachment_action-8.0.1.0.0-py2.7-nspkg.pth
odoo8_addon_attachment_action-8.0.1.0.0.dist-info/METADATA
odoo8_addon_attachment_action-8.0.1.0.0.dist-info/RECORD
odoo8_addon_attachment_action-8.0.1.0.0.dist-info/WHEEL
odoo8_addon_attachment_action-8.0.1.0.0.dist-info/namespace_packages.txt
odoo8_addon_attachment_action-8.0.1.0.0.dist-info/top_level.txt
odoo_addons/attachment_action/README.rst
odoo_addons/attachment_action/__init__.py
odoo_addons/attachment_action/__openerp__.py
odoo_addons/attachment_action/static/description/icon.png
odoo_addons/attachment_action/static/src/css/attachment_action.css
odoo_addons/attachment_action/static/src/js/attachment_action.js
odoo_addons/attachment_action/static/src/xml/attachment_action.xml
odoo_addons/attachment_action/views/templates.xml
